fish_util/__init__.py
fish_util/main.py
fish_util/lib/__init__.py
fish_util/lib/ez_emoji/__init__.py
fish_util/lib/ez_emoji/core.py
fish_util/lib/ez_emoji/py.typed
fish_util/lib/ez_emoji/tokenizer.py
fish_util/lib/ez_emoji/unicode_codes/__init__.py
fish_util/lib/ez_emoji/unicode_codes/data_dict.py
fish_util/src/__init__.py
fish_util/src/collections_util.py
fish_util/src/common_op.py
fish_util/src/conf_allure.py
fish_util/src/config_util.py
fish_util/src/content_format.py
fish_util/src/datetime_util.py
fish_util/src/decorator_util.py
fish_util/src/decorator_util2.py
fish_util/src/file_util.py
fish_util/src/file_util2.py
fish_util/src/file_util3.py
fish_util/src/http_util.py
fish_util/src/internal_var.py
fish_util/src/log_util.py
fish_util/src/log_util2.py
fish_util/src/log_util3.py
fish_util/src/logging_util.py
fish_util/src/loguru_util.py
fish_util/src/moment_util.py
fish_util/src/read_config.py
fish_util/src/shell_util.py
fish_util/src/string_util.py
fish_util/src/sysinfo_util.py
fish_util/src/time_util.py
fish_util/src/utils.py
fish_util/src/yaml_util.py
fish_util/src/archive/AliUtil.py
fish_util/src/archive/BaiduUtil.py
fish_util/src/archive/CSVUtil.py
fish_util/src/archive/ChromeUtil 1.py
fish_util/src/archive/ChromeUtil.py
fish_util/src/archive/DateUtil.py
fish_util/src/archive/EzUtil.py
fish_util/src/archive/FTPUtil.py
fish_util/src/archive/FileUtil.py
fish_util/src/archive/FolderUtil-backup.py
fish_util/src/archive/FolderUtil.py
fish_util/src/archive/HuluUtil.py
fish_util/src/archive/LogUtil.py
fish_util/src/archive/PostManUtil.py
fish_util/src/archive/ReUtil.py
fish_util/src/archive/SeleniumUtil.py
fish_util/src/archive/StringUtil.py
fish_util/src/archive/SystemUtil.py
fish_util/src/archive/TimeUtil.py
fish_util/src/archive/WordUtil.py
fish_util/src/archive/__init__.py
fish_util/src/archive/alfred_util.py
fish_util/src/archive/asyncio_util.py
fish_util/src/archive/baidu_translate.py
fish_util/src/archive/database_util.py
fish_util-1.0.37.dist-info/METADATA
fish_util-1.0.37.dist-info/WHEEL
fish_util-1.0.37.dist-info/top_level.txt
fish_util-1.0.37.dist-info/RECORD
