Metadata-Version: 2.1
Name: fish_util
Version: 1.0.37
Summary: Fishyer's Python Util Library
Home-page: https://github.com/fishyer/fish_util
Author: Fishyer
Author-email: yutianran666@gmail.com
Classifier: Programming Language :: Python :: 3
Classifier: License :: OSI Approved :: MIT License
